{
  "menu": [
    {
      "name": "Dashboard",
      "icon": "menu-icon ti tabler-smart-home",
      "slug": "dashboard",
      "url": "/dashboard"
    },
    {
      "menuHeader": "Kelas Saya",
      "icon": "menu-icon ti tabler-door"
    },
    {
      "name": "Input Absensi Kelas",
      "icon": "menu-icon ti tabler-edit",
      "slug": "admin.absensi-cepat",
      "url": "/admin/absensi-cepat"
    },
    {
      "name": "Absensi Harian Kelas",
      "icon": "menu-icon ti tabler-calendar-stats",
      "slug": "wali-kelas.absensi-siswa.index",
      "url": "/wali-kelas/absensi-siswa"
    },
    {
      "name": "Data Siswa Kelas",
      "icon": "menu-icon ti tabler-users",
      "slug": "wali-kelas.siswa.index",
      "url": "/wali-kelas/siswa"
    },
    {
      "name": "Laporan Rekap",
      "icon": "menu-icon ti tabler-presentation",
      "slug": "wali-kelas.rekap-harian",
      "url": "/wali-kelas/rekap-harian"
    },
    {
      "menuHeader": "Tugas Piket",
      "icon": "menu-icon ti tabler-shield-check"
    },
    {
      "name": "Monitor Piket",
      "icon": "menu-icon ti tabler-device-desktop-analytics",
      "slug": [
        "public.scan-qr.index",
        "public.live-board"
      ],
      "submenu": [
        {
          "name": "Scanner QR Piket",
          "icon": "menu-icon ti tabler-qrcode",
          "slug": "public.scan-qr.index",
          "url": "/scan-qr",
          "target": "_blank"
        },
        {
          "name": "Live Board Monitor",
          "icon": "menu-icon ti tabler-screen-share",
          "slug": "public.live-board",
          "url": "/live-board",
          "target": "_blank"
        }
      ]
    },
    {
      "name": "Absensi Kegiatan",
      "icon": "menu-icon ti tabler-calendar-event",
      "slug": [
        "admin.kegiatans.absensi",
        "admin.absensi-kegiatan.scan"
      ],
      "submenu": [
        {
          "name": "Daftar Kegiatan",
          "icon": "menu-icon ti tabler-list",
          "slug": "admin.kegiatans.absensi",
          "url": "/admin/kegiatans/absensi"
        },
        {
          "name": "Scan Kegiatan Khusus",
          "icon": "menu-icon ti tabler-qrcode",
          "slug": "admin.absensi-kegiatan.scan",
          "url": "/admin/absensi-kegiatan/scan"
        }
      ]
    },
    {
      "name": "Ekstrakurikuler",
      "icon": "menu-icon ti tabler-star",
      "slug": [
        "admin.ekskul"
      ],
      "url": "/admin/ekskul"
    },
    {
      "name": "Poin Pelanggaran",
      "icon": "menu-icon ti tabler-swords",
      "slug": ["admin.pelanggaran-siswa.index", "admin.pelanggaran-siswa.create", "admin.pelanggaran-siswa.rekap"],
      "submenu": [
        {
          "name": "Daftar Pelanggaran",
          "slug": "admin.pelanggaran-siswa.index",
          "url": "/admin/pelanggaran-siswa"
        },
        {
          "name": "Tambah Pelanggaran",
          "slug": "admin.pelanggaran-siswa.create",
          "url": "/admin/pelanggaran-siswa/create"
        },
        {
          "name": "Rekap Pelanggaran",
          "slug": "admin.pelanggaran-siswa.rekap",
          "url": "/admin/pelanggaran-siswa/rekap"
        }
      ]
    },
    {
      "menuHeader": "Portal Guru",
      "icon": "menu-icon ti tabler-user-cog"
    },
    {
      "name": "Absensi Saya",
      "icon": "menu-icon ti tabler-user-check",
      "slug": "guru.absensi.scan",
      "url": "/guru/absensi/scan"
    },
    {
      "name": "Pengajuan Izin",
      "icon": "menu-icon ti tabler-stethoscope",
      "slug": "guru.izin-sakit.index",
      "url": "/guru/izin-sakit"
    },
    {
      "name": "Penugasan Siswa",
      "icon": "menu-icon ti tabler-book-upload",
      "slug": "assignments",
      "url": "/guru/assignments"
    }
  ]
}